cron_migration/__init__.py
cron_migration/conf.py
cron_migration/app/__init__.py
cron_migration/app/exit_codes.py
cron_migration/app/manager.py
cron_migration/app/models/__init__.py
cron_migration/app/models/environment.py
cron_migration/cli/__init__.py
cron_migration/cli/commands.py
cron_migration/cli/facade.py
cron_migration/cli/manager.py
cron_migration/cli/output.py
cron_migration/cli/models/__init__.py
cron_migration/cli/models/command.py
cron_migration/cli/models/commandError.py
cron_migration/cli/operations/__init__.py
cron_migration/cli/operations/downgrade.py
cron_migration/cli/operations/init.py
cron_migration/cli/operations/make_revision.py
cron_migration/cli/operations/upgrade.py
cron_migration/files/__init__.py
cron_migration/files/managers/__init__.py
cron_migration/files/managers/files.py
cron_migration/files/managers/path.py
cron_migration/files/models/__init__.py
cron_migration/files/models/path.py
cron_migration/files/services/__init__.py
cron_migration/files/services/path.py
cron_migration/revisions/__init__.py
cron_migration/revisions/manager.py
cron_migration/revisions/model.py
cron_migration/revisions/task.py
cron_migration/revisions/services/__init__.py
cron_migration/revisions/services/downgrade.py
cron_migration/revisions/services/mapper.py
cron_migration/revisions/services/new_revision.py
cron_migration/revisions/services/revision_apply.py
cron_migration/suits/__init__.py
cron_migration/suits/crontab/__init__.py
cron_migration/suits/crontab/crontab.py
cron_migration/suits/crontab/driver.py
cron_migration/suits/crontab/job.py
cron_migration/suits/crontab/scheduler.py
cron_migration/suits/crontab/utils.py
cron_migration/system/__init__.py
cron_migration/system/meta/__init__.py
cron_migration/system/meta/proxies.py
cron_migration/system/meta/singleton.py
cron_migration/templates/default/conf.py
cron_migration/templates/default/revision.py.mako
itay_bardugo_cron_migration-1.1.36.dist-info/LICENSE
itay_bardugo_cron_migration-1.1.36.dist-info/METADATA
itay_bardugo_cron_migration-1.1.36.dist-info/WHEEL
itay_bardugo_cron_migration-1.1.36.dist-info/entry_points.txt
itay_bardugo_cron_migration-1.1.36.dist-info/top_level.txt
itay_bardugo_cron_migration-1.1.36.dist-info/RECORD
