Metadata-Version: 2.1
Name: itay-bardugo-cron-migration
Version: 1.1.36
Summary: manage your cron jobs with python and a revision system(CLI)
Home-page: https://github.com/itay-bardugo/python-cron-migration
Author: Itay Bardugo
Author-email: itaybardugo91@gmail.com
License: UNKNOWN
Platform: UNKNOWN
Classifier: Programming Language :: Python :: 3.8
Classifier: License :: OSI Approved :: MIT License
Classifier: Operating System :: Unix
Requires-Python: >=3.8.3
Requires-Dist: click (==7.1.2)
Requires-Dist: Mako (==1.1.2)
Requires-Dist: MarkupSafe (==1.1.1)
Requires-Dist: python-dateutil (==2.8.1)
Requires-Dist: python-editor (==1.0.4)
Requires-Dist: six (==1.14.0)
